{
  "po" : 
  {
    "en_US" : 
    {
      "branch" : "",
      "commit" : 
      {
        "date" : "",
        "hash" : "",
        "title" : ""
      }
    },
    "ru_RU" : 
    {
      "branch" : "master",
      "commit" : 
      {
        "date" : "2025-10-13 00:04:44 -0400",
        "hash" : "c9ffe0b9a18a477066f252dd004605352ad9d6b5",
        "title" : "CMake Nightly Date Stamp"
      }
    },
    "zh_CN" : 
    {
      "branch" : "master",
      "commit" : 
      {
        "date" : "2025-10-13 00:04:44 -0400",
        "hash" : "c9ffe0b9a18a477066f252dd004605352ad9d6b5",
        "title" : "CMake Nightly Date Stamp"
      }
    },
    "zh_TW" : 
    {
      "branch" : "master",
      "commit" : 
      {
        "date" : "2025-10-13 00:04:44 -0400",
        "hash" : "c9ffe0b9a18a477066f252dd004605352ad9d6b5",
        "title" : "CMake Nightly Date Stamp"
      }
    }
  },
  "pot" : 
  {
    "branch" : "master",
    "commit" : 
    {
      "date" : "2025-10-13 00:04:44 -0400",
      "hash" : "c9ffe0b9a18a477066f252dd004605352ad9d6b5",
      "title" : "CMake Nightly Date Stamp"
    }
  },
  "type" : "branch",
  "version" : "master"
}